philoch_bib_sdk/__init__.py
philoch_bib_sdk/_rust.cpython-313-darwin.so
philoch_bib_sdk/_rust.pyi
philoch_bib_sdk/adapters/io/__init__.py
philoch_bib_sdk/adapters/io/csv/__init__.py
philoch_bib_sdk/adapters/io/ods/__init__.py
philoch_bib_sdk/adapters/plaintext/bibitem_reader.py
philoch_bib_sdk/adapters/tabular_data/read_journal_volume_number_index.py
philoch_bib_sdk/converters/latex.py
philoch_bib_sdk/converters/plaintext/author/formatter.py
philoch_bib_sdk/converters/plaintext/author/parser.py
philoch_bib_sdk/converters/plaintext/bib_string_formatter.py
philoch_bib_sdk/converters/plaintext/bibitem/bibkey_formatter.py
philoch_bib_sdk/converters/plaintext/bibitem/bibkey_parser.py
philoch_bib_sdk/converters/plaintext/bibitem/date_formatter.py
philoch_bib_sdk/converters/plaintext/bibitem/date_parser.py
philoch_bib_sdk/converters/plaintext/bibitem/formatter.py
philoch_bib_sdk/converters/plaintext/bibitem/pages_formatter.py
philoch_bib_sdk/converters/plaintext/bibitem/pages_parser.py
philoch_bib_sdk/converters/plaintext/bibitem/parser.py
philoch_bib_sdk/converters/plaintext/journal/formatter.py
philoch_bib_sdk/converters/plaintext/journal/parser.py
philoch_bib_sdk/converters/plaintext/shared/renderable_formatter.py
philoch_bib_sdk/interfaces/cli/__init__.py
philoch_bib_sdk/interfaces/cli/fuzzy_matching.py
philoch_bib_sdk/logic/__init__.py
philoch_bib_sdk/logic/default_models.py
philoch_bib_sdk/logic/functions/__init__.py
philoch_bib_sdk/logic/functions/comparator.py
philoch_bib_sdk/logic/functions/fuzzy_matcher.py
philoch_bib_sdk/logic/functions/journal_article_matcher.py
philoch_bib_sdk/logic/literals.py
philoch_bib_sdk/logic/models.py
philoch_bib_sdk/logic/models_staging.py
philoch_bib_sdk/procedures/fuzzy_matching.py
philoch_bib_sdk/py.typed
philoch_bib_sdk-0.4.2.dist-info/METADATA
philoch_bib_sdk-0.4.2.dist-info/WHEEL
philoch_bib_sdk-0.4.2.dist-info/licenses/LICENSE
philoch_bib_sdk-0.4.2.dist-info/RECORD
