Metadata-Version: 2.4
Name: philoch-bib-sdk
Version: 0.4.2
Requires-Dist: aletk>=0.1.6
Requires-Dist: attrs>=25.3.0
Requires-Dist: polars>=1.32.3
Requires-Dist: pydantic>=2.11.9
Requires-Dist: cytoolz>=1.0.1
License-File: LICENSE
Summary: Standard development kit for the Philosophie Bibliography project
Author-email: Luis Alejandro Bordo García <luis.bordo@philosophie.ch>
Maintainer-email: Luis Alejandro Bordo García <tech@philosophie.ch>
License: MIT
Requires-Python: >=3.13
